Workbook
Name percentual_renda: Simulador!$F$9
Name renda: Simulador!$B$9
Name rentabilidade_carteira: Simulador!$Q$9
Name rentabilidade_DY: Simulador!$Q$12
Name tempo: Simulador!$L$12
Name valor: Simulador!$L$9

Sheet Simulador
C5: 1. DADOS DO INVESTIDOR | L5: 2. MEU INVESTIMENTO
B6: Comece informando sua renda mensal para calcularmos uma sugestão de valor para investir. | L6: Defina seu plano de investimento preenchendo os campos em azul.
B8: Qual é a sua renda mensal? | F8: Percentual sugerido | L8: Quanto deseja investir por mês? | Q8: Crescimento mensal estimado do patrimônio
B9: 2000 | F9: 0.2 | L9: 200 | Q9: 0.01079
B10: Valor sugerido para investir
L11: Por quantos anos deseja investir? | Q11: Rendimento mensal estimado dos dividendos (DY)
B12: =renda*percentual_renda -> 400 | L12: 5 | Q12: 0.006
C14: 3. RESULTADOS DA SIMULAÇÃO | T14: Veja a projeção do seu investimento considerando os valores informados.
B16: TOTAL INVESTIDO | K16: PATRIMÔNIO PROJETADO | Q16: DIVIDENDOS/MÊS ESTIMADOS
B17: =valor*tempo*12 -> 12000 | K17: =FV(rentabilidade_carteira,tempo*12,valor*-1) -> 16755.383 | Q17: =K17*rentabilidade_DY -> 100.5323
C20: 4. PROJEÇÃO DE FUTURO | T20: Veja como seu investimento pode evoluir ao longo do tempo mantendo os aportes.
B22: Prazo | C22: Total investido | G22: Patrimônio projetado | K22: Dividendos/mês
A23: 2 | B23: Em 2 anos | C23: =valor*A23*12 -> 4800 | G23: =FV(rentabilidade_carteira,A23*12,valor*-1) -> 5445.5255 | K23: =G23*rentabilidade_DY -> 32.673153
A24: 5 | B24: Em 5 anos | C24: =valor*A24*12 -> 12000 | G24: =FV(rentabilidade_carteira,A24*12,valor*-1) -> 16755.383 | K24: =G24*rentabilidade_DY -> 100.5323
A25: 10 | B25: Em 10 anos | C25: =valor*A25*12 -> 24000 | G25: =FV(rentabilidade_carteira,A25*12,valor*-1) -> 48656.843 | K25: =G25*rentabilidade_DY -> 291.94106
A26: 20 | B26: Em 20 anos | C26: =valor*A26*12 -> 48000 | G26: =FV(rentabilidade_carteira,A26*12,valor*-1) -> 225039.68 | K26: =G26*rentabilidade_DY -> 1350.2381
A27: 30 | B27: Em 30 anos | C27: =valor*A27*12 -> 72000 | G27: =FV(rentabilidade_carteira,A27*12,valor*-1) -> 864433.93 | K27: =G27*rentabilidade_DY -> 5186.6036
C30: 5. PERFIL DO INVESTIDOR
C31: O perfil de investidor representa o nível de risco que você está disposto a assumir. O conservador prioriza segurança e preservação do patrimônio; o moderado busca equilíbrio entre segurança e rentabilidade; e o agressivo aceita maiores oscilações em busca de maior potencial de retorno. Selecione o perfil que mais combina com você e veja uma sugestão de distribuição do seu investimento.
F33: Distribuição sugerida por tipo de FII | O33: Distribuição por Tipo de FII
B34: Qual é o seu perfil | F34: Tipo de FII | H34: Percentual | K34: Valor mensal
B35: Moderado | F35: Papel | H35: =VLOOKUP($B$35&"-"&F35,perfil!$A$3:$D$20,4,FALSE) -> 0.32 | K35: =H35*valor -> 64
F36: Tijolo | H36: =VLOOKUP($B$35&"-"&F36,perfil!$A$3:$D$20,4,FALSE) -> 0.35 | K36: =H36*valor -> 70
F37: Híbridos | H37: =VLOOKUP($B$35&"-"&F37,perfil!$A$3:$D$20,4,FALSE) -> 0.08 | K37: =H37*valor -> 16
F38: FOFs | H38: =VLOOKUP($B$35&"-"&F38,perfil!$A$3:$D$20,4,FALSE) -> 0.05 | K38: =H38*valor -> 10
F39: Desenvolvimento | H39: =VLOOKUP($B$35&"-"&F39,perfil!$A$3:$D$20,4,FALSE) -> 0.1 | K39: =H39*valor -> 20
F40: Hotelarias | H40: =VLOOKUP($B$35&"-"&F40,perfil!$A$3:$D$20,4,FALSE) -> 0.1 | K40: =H40*valor -> 20
F41: Total | H41: =SUM(H35:H40) -> 1 | K41: =SUM(K35:K40) -> 200
B44: Seu futuro financeiro começa com as escolhas de hoje.
B45: Com planejamento, consistência e disciplina, seus investimentos contribuem para a construção de novos objetivos e maior tranquilidade financeira ao longo do tempo.
B46: Continue investindo em você.

Sheet perfil
A2: CHAVE | B2: PERFIL | C2: TIPO DE FII | D2: %
A3: =B3&"-"&C3 -> Conservador-Tijolo | B3: Conservador | C3: Tijolo | D3: 0.5
A4: =B4&"-"&C4 -> Conservador-Papel | B4: Conservador | C4: Papel | D4: 0.3
A5: =B5&"-"&C5 -> Conservador-Híbridos | B5: Conservador | C5: Híbridos | D5: 0.1
A6: =B6&"-"&C6 -> Conservador-FOFs | B6: Conservador | C6: FOFs | D6: 0.1
A7: =B7&"-"&C7 -> Conservador-Desenvolvimento | B7: Conservador | C7: Desenvolvimento | D7: 0
A8: =B8&"-"&C8 -> Conservador-Hotelarias | B8: Conservador | C8: Hotelarias | D8: 0
A9: =B9&"-"&C9 -> Moderado-Tijolo | B9: Moderado | C9: Tijolo | D9: 0.35
A10: =B10&"-"&C10 -> Moderado-Papel | B10: Moderado | C10: Papel | D10: 0.32
A11: =B11&"-"&C11 -> Moderado-Híbridos | B11: Moderado | C11: Híbridos | D11: 0.08
A12: =B12&"-"&C12 -> Moderado-FOFs | B12: Moderado | C12: FOFs | D12: 0.05
A13: =B13&"-"&C13 -> Moderado-Desenvolvimento | B13: Moderado | C13: Desenvolvimento | D13: 0.1
A14: =B14&"-"&C14 -> Moderado-Hotelarias | B14: Moderado | C14: Hotelarias | D14: 0.1
... A20: =B20&"-"&C20 -> Agressivo-Hotelarias | B20: Agressivo | C20: Hotelarias | D20: 0.1
